<?xml version="1.0" encoding="UTF-8"?>
<databaseChangeLog
        xmlns="http://www.liquibase.org/xml/ns/dbchangelog"
        xmlns:xsi="http://www.w3.org/2001/XMLSchema-instance"
        xsi:schemaLocation="http://www.liquibase.org/xml/ns/dbchangelog
                      http://www.liquibase.org/xml/ns/dbchangelog/dbchangelog-4.27.xsd"
        objectQuotingStrategy="QUOTE_ONLY_RESERVED_WORDS">
    <changeSet id="1728661113633-1" author="artur">
        <createTable tableName="comment">
            <column autoIncrement="true" name="id" type="BIGINT">
                <constraints nullable="false" primaryKey="true" primaryKeyName="pk_comment"/>
            </column>
            <column name="content" type="VARCHAR(255)"/>
            <column name="camping_route_id" type="BIGINT"/>
        </createTable>
    </changeSet>
    <changeSet id="1728661113633-2" author="artur">
        <addForeignKeyConstraint baseColumnNames="camping_route_id" baseTableName="comment"
                                 constraintName="FK_COMMENT_ON_CAMPINGROUTE" referencedColumnNames="id"
                                 referencedTableName="camping_route"/>
    </changeSet>

</databaseChangeLog>